lndb_app/__init__.py
lndb_app/__main__.py
lndb_app/_core.py
lndb_app-0.0.2.dist-info/entry_points.txt
lndb_app-0.0.2.dist-info/WHEEL
lndb_app-0.0.2.dist-info/METADATA
lndb_app-0.0.2.dist-info/RECORD
