Metadata-Version: 2.1
Name: lndb_app
Version: 0.0.2
Summary: Web app to interact with Lamin instances.
Author-email: Lamin Labs <laminlabs@gmail.com>
Requires-Dist: nbproject
Requires-Dist: lamindb
Requires-Dist: lndb
Requires-Dist: pre-commit ; extra == "dev"
Requires-Dist: nox ; extra == "dev"
Requires-Dist: pytest>=6.0 ; extra == "test"
Requires-Dist: pytest-cov ; extra == "test"
Project-URL: Home, https://github.com/laminlabs/lndb-app
Provides-Extra: dev
Provides-Extra: test
